setup.py
mapascii/__init__.py
mapascii/map.py
mapascii.egg-info/PKG-INFO
mapascii.egg-info/SOURCES.txt
mapascii.egg-info/dependency_links.txt
mapascii.egg-info/top_level.txt