Metadata-Version: 2.1
Name: mapascii
Version: 1.0.0
Summary: A small array-based class for maps
Author: meiscool466
Author-email: meiscool466@gmail.com
Keywords: array class maps ascii
Classifier: Development Status :: 5 - Production/Stable
Classifier: Intended Audience :: Developers
Classifier: Topic :: Multimedia :: Graphics
Classifier: Programming Language :: Python
Classifier: Programming Language :: Python :: 3
